[{"name":"Starbucks","location":{"type":"Point","coordinates":[-122.4084517461,37.7891481546]},"local":"starbucks"},{"name":"Starbucks","location":{"type":"Point","coordinates":[-122.4075222681,37.787988923]},"local":"starbucks"},{"name":"Starbucks","location":{"type":"Point","coordinates":[-122.4106742,37.78712238]},"local":"starbucks"},{"name":"Starbucks","location":{"type":"Point","coordinates":[-122.40682,37.78936]},"local":"starbucks"},{"name":"Starbucks","location":{"type":"Point","coordinates":[-122.40906,37.78617]},"local":"starbucks"},{"name":"Starbucks","location":{"type":"Point","coordinates":[-122.4057733,37.79042546]},"local":"starbucks"},{"name":"Starbucks","location":{"type":"Point","coordinates":[-122.4056946,37.78615912]},"local":"starbucks"},{"name":"Chisme","location":{"type":"Point","coordinates":[-122.4148023971,37.7884671561]},"local":"vegan"},{"name":"Starbucks","location":{"type":"Point","coordinates":[-122.4075961178,37.7841431437]},"local":"starbucks"},{"name":"Starbucks","location":{"type":"Point","coordinates":[-122.4040255818,37.7908174192]},"local":"starbucks"},{"name":"Starbucks","location":{"type":"Point","coordinates":[-122.40318,37.78736]},"local":"starbucks"},{"name":"Starbucks","location":{"type":"Point","coordinates":[-122.4040778421,37.7846048234]},"local":"starbucks"},{"name":"Starbucks","location":{"type":"Point","coordinates":[-122.402032,37.789594]},"local":"starbucks"},{"name":"Starbucks","location":{"type":"Point","coordinates":[-122.40354,37.79219]},"local":"starbucks"},{"name":"Starbucks","location":{"type":"Point","coordinates":[-122.4042928219,37.7928208876]},"local":"starbucks"},{"name":"Starbucks","location":{"type":"Point","coordinates":[-122.4039853612,37.7842313689]},"local":"starbucks"},{"name":"Starbucks","location":{"type":"Point","coordinates":[-122.4007102485,37.7887916506]},"local":"starbucks"},{"name":"Nourish Cafe","location":{"type":"Point","coordinates":[-122.4172961543,37.7905285343]},"local":"vegan"},{"name":"CDC Executive Sedan and Limo transportation, SFO","location":{"type":"Point","coordinates":[-122.4177474,37.7871076]},"local":"travel"},{"name":"Starbucks","location":{"type":"Point","coordinates":[-122.4009510945,37.7911044959]},"local":"starbucks"},{"name":"Jane","location":{"type":"Point","coordinates":[-122.4182649141,37.7865138769]},"local":"vegan"},{"name":"Starbucks","location":{"type":"Point","coordinates":[-122.40268,37.794613]},"local":"starbucks"},{"name":"Olea","location":{"type":"Point","coordinates":[-122.4190000622,37.7908686839]},"local":"vegan"},{"name":"Ike's Sandwiches","location":{"type":"Point","coordinates":[-122.4196290626,37.7851455976]},"local":"vegan"},{"name":"Vegan Picnic Polk St","location":{"type":"Point","coordinates":[-122.420448,37.788959]},"local":"vegan"},{"name":"Kasa Indian Eatery","location":{"type":"Point","coordinates":[-122.4204494248,37.7896553215]},"local":"vegan"},{"name":"Starbucks","location":{"type":"Point","coordinates":[-122.3975822,37.78946201]},"local":"starbucks"},{"name":"Batter Bakery","location":{"type":"Point","coordinates":[-122.4207755503,37.7895513579]},"local":"vegan"},{"name":"Thai Idea Vegetarian Restaurant","location":{"type":"Point","coordinates":[-122.419141,37.783395]},"local":"vegan"},{"name":"Brenda's French Soul Food","location":{"type":"Point","coordinates":[-122.41889745,37.7828964091]},"local":"vegan"},{"name":"Starbucks","location":{"type":"Point","coordinates":[-122.3966218115,37.7896507952]},"local":"starbucks"},{"name":"Starbucks","location":{"type":"Point","coordinates":[-122.3966867519,37.7857823575]},"local":"starbucks"},{"name":"Starbucks","location":{"type":"Point","coordinates":[-122.42222,37.788567]},"local":"starbucks"},{"name":"Starbucks","location":{"type":"Point","coordinates":[-122.422066,37.790268]},"local":"starbucks"},{"name":"Stoner's","location":{"type":"Point","coordinates":[-122.4205,37.782448]},"local":"vegan"},{"name":"Starbucks","location":{"type":"Point","coordinates":[-122.39561,37.79011]},"local":"starbucks"},{"name":"Invisa Logistic Services inc.","location":{"type":"Point","coordinates":[-122.4209899902,37.7821502686]},"local":"travel"},{"name":"Whole Foods Market","location":{"type":"Point","coordinates":[-122.4233835631,37.7900143916]},"local":"vegan"},{"name":"Starbucks Reserve","location":{"type":"Point","coordinates":[-122.395215301,37.7915737346]},"local":"starbucks"},{"name":"Starbucks","location":{"type":"Point","coordinates":[-122.4172976,37.77708998]},"local":"starbucks"},{"name":"Starbucks","location":{"type":"Point","coordinates":[-122.4220575745,37.7967981384]},"local":"starbucks"},{"name":"Woodblock","location":{"type":"Point","coordinates":[-122.421525,37.778018]},"local":"vegan"},{"name":"Baia","location":{"type":"Point","coordinates":[-122.421775,37.77815]},"local":"vegan"},{"name":"Starbucks","location":{"type":"Point","coordinates":[-122.4029817,37.80284116]},"local":"starbucks"},{"name":"Waraku","location":{"type":"Point","coordinates":[-122.4287679073,37.7857204549]},"local":"vegan"},{"name":"San Wang Restaurant","location":{"type":"Point","coordinates":[-122.4293957161,37.7857382965]},"local":"vegan"},{"name":"Blue Bottle Coffee","location":{"type":"Point","coordinates":[-122.4232236012,37.7764301318]},"local":"vegan"},{"name":"Benkyodo","location":{"type":"Point","coordinates":[-122.4300526301,37.7864224821]},"local":"vegan"},{"name":"Urban Remedy","location":{"type":"Point","coordinates":[-122.4241549015,37.7766503143]},"local":"vegan"},{"name":"Smitten Ice Cream","location":{"type":"Point","coordinates":[-122.4242347862,37.7762728786]},"local":"vegan"},{"name":"Patxi's Chicago Pizza","location":{"type":"Point","coordinates":[-122.4249166115,37.7765487334]},"local":"vegan"}]